{
    "tag_to_idx": {
        "alat_elektronik": 0,
        "aplikasi": 1,
        "barcode": 2,
        "bekerja": 3,
        "belajar": 4,
        "berenang": 5,
        "berkendara": 6,
        "bermain": 7,
        "bermain_game": 8,
        "berpose": 9,
        "berwarna": 10,
        "blur": 11,
        "buku": 12,
        "chat": 13,
        "dapur": 14,
        "dokumen": 15,
        "foto_keluarga": 16,
        "gelap": 17,
        "hewan": 18,
        "ilustrasi": 19,
        "jalan": 20,
        "kantor": 21,
        "kelas": 22,
        "mainan": 23,
        "makan": 24,
        "makanan": 25,
        "mal": 26,
        "meja_kursi": 27,
        "meme": 28,
        "mobil": 29,
        "monokrom": 30,
        "motor": 31,
        "ocr_worthy": 32,
        "olahraga": 33,
        "pantai": 34,
        "pegunungan": 35,
        "rumah": 36,
        "screenshot": 37,
        "selfie": 38,
        "sepeda": 39,
        "taman": 40,
        "tanaman": 41,
        "tempat_ibadah": 42,
        "terang": 43,
        "tidur": 44
    },
    "idx_to_tag": {
        "alat_elektronik": 0,
        "aplikasi": 1,
        "barcode": 2,
        "bekerja": 3,
        "belajar": 4,
        "berenang": 5,
        "berkendara": 6,
        "bermain": 7,
        "bermain_game": 8,
        "berpose": 9,
        "berwarna": 10,
        "blur": 11,
        "buku": 12,
        "chat": 13,
        "dapur": 14,
        "dokumen": 15,
        "foto_keluarga": 16,
        "gelap": 17,
        "hewan": 18,
        "ilustrasi": 19,
        "jalan": 20,
        "kantor": 21,
        "kelas": 22,
        "mainan": 23,
        "makan": 24,
        "makanan": 25,
        "mal": 26,
        "meja_kursi": 27,
        "meme": 28,
        "mobil": 29,
        "monokrom": 30,
        "motor": 31,
        "ocr_worthy": 32,
        "olahraga": 33,
        "pantai": 34,
        "pegunungan": 35,
        "rumah": 36,
        "screenshot": 37,
        "selfie": 38,
        "sepeda": 39,
        "taman": 40,
        "tanaman": 41,
        "tempat_ibadah": 42,
        "terang": 43,
        "tidur": 44
    }
}